containers/__init__.py
containers/data_types.py
containers/providers/__init__.py
containers/providers/base.py
containers/providers/helpers.py
containers/providers/podman.py
containers/services/__init__.py
containers/services/base.py
containers/services/windows.py
docker/containers/layer_archive.json
docker/containers/mount_chown.json
container_helpers-0.0.12.dist-info/METADATA
container_helpers-0.0.12.dist-info/WHEEL
container_helpers-0.0.12.dist-info/licenses/LICENSE
container_helpers-0.0.12.dist-info/RECORD
