Metadata-Version: 2.4
Name: container-helpers
Version: 0.0.12
Summary: Helpers for running docker or podman containers easily in Python
Project-URL: Repository, https://github.com/LaunchPlatform/container-helpers
Author-email: Fang-Pen Lin <fangpen@launchplatform.com>
License-Expression: MIT
License-File: LICENSE
Requires-Python: ~=3.9
